trex_stl_lib/__init__.py
trex_stl_lib/api.py
trex_stl_lib/trex_stl_async_client.py
trex_stl_lib/trex_stl_client.py
trex_stl_lib/trex_stl_conn.py
trex_stl_lib/trex_stl_exceptions.py
trex_stl_lib/trex_stl_ext.py
trex_stl_lib/trex_stl_hltapi.py
trex_stl_lib/trex_stl_jsonrpc_client.py
trex_stl_lib/trex_stl_packet_builder_interface.py
trex_stl_lib/trex_stl_packet_builder_scapy.py
trex_stl_lib/trex_stl_port.py
trex_stl_lib/trex_stl_psv.py
trex_stl_lib/trex_stl_sim.py
trex_stl_lib/trex_stl_stats.py
trex_stl_lib/trex_stl_std.py
trex_stl_lib/trex_stl_streams.py
trex_stl_lib/trex_stl_types.py
trex_stl_lib/trex_stl_vlan.py
trex_stl_lib/trex_stl_wlc.py
trex_stl_lib/rx_services/__init__.py
trex_stl_lib/rx_services/trex_stl_rx_service_api.py
trex_stl_lib/rx_services/trex_stl_rx_service_ipv6.py
trex_stl_lib/services/__init__.py
trex_stl_lib/services/trex_stl_ap.py
trex_stl_lib/services/trex_stl_dhcp_parser.py
trex_stl_lib/services/trex_stl_service.py
trex_stl_lib/services/trex_stl_service_arp.py
trex_stl_lib/services/trex_stl_service_dhcp.py
trex_stl_lib/services/trex_stl_service_fast_parser.py
trex_stl_lib/services/trex_stl_service_icmp.py
trex_stl_lib/services/trex_stl_service_int.py
trex_stl_lib/utils/GAObjClass.py
trex_stl_lib/utils/__init__.py
trex_stl_lib/utils/common.py
trex_stl_lib/utils/constants.py
trex_stl_lib/utils/filters.py
trex_stl_lib/utils/parsing_opts.py
trex_stl_lib/utils/pcap.py
trex_stl_lib/utils/text_opts.py
trex_stl_lib/utils/text_tables.py
trex_stl_lib/utils/zipmsg.py
trex_stl_lib-0.3.dist-info/METADATA
trex_stl_lib-0.3.dist-info/WHEEL
trex_stl_lib-0.3.dist-info/top_level.txt
trex_stl_lib-0.3.dist-info/RECORD
